LICENSE
README.md
setup.py
chromatictools/__init__.py
chromatictools/badges.py
chromatictools/cli.py
chromatictools/colors.py
chromatictools/functional.py
chromatictools/imports.py
chromatictools/math.py
chromatictools/pickle.py
chromatictools/purgithub.py
chromatictools/unitdoctest.py
chromatictools/unittestmixins.py
chromatictools.egg-info/PKG-INFO
chromatictools.egg-info/SOURCES.txt
chromatictools.egg-info/dependency_links.txt
chromatictools.egg-info/requires.txt
chromatictools.egg-info/top_level.txt