Metadata-Version: 2.1
Name: chromatictools
Version: 0.0.8
Summary: chromatictools
Home-page: https://github.com/ChromaticIsobar/chromatictools
Author: Marco Tiraboschi
Author-email: marco.tiraboschi@unimi.it
Maintainer: Marco Tiraboschi
Maintainer-email: marco.tiraboschi@unimi.it
License: UNKNOWN
Platform: UNKNOWN
Classifier: Programming Language :: Python :: 3
Classifier: License :: OSI Approved :: MIT License
Classifier: Operating System :: OS Independent
Requires-Python: >=3.6
Provides-Extra: docs
Provides-Extra: lint
Provides-Extra: cov
